tests/__init__.py
tests/test_writer.py
wandb_tsbw/__init__.py
wandb_tsbw/writer.py
wandb_tsbw-0.1.0.dist-info/METADATA
wandb_tsbw-0.1.0.dist-info/WHEEL
wandb_tsbw-0.1.0.dist-info/top_level.txt
wandb_tsbw-0.1.0.dist-info/RECORD
