Metadata-Version: 2.4
Name: wandb_tsbw
Version: 0.1.0
Summary: A compatibility layer for TensorBoard's SummaryWriter to log to Weights & Biases
Home-page: https://github.com/yourusername/wandb_tsbw
Author: Your Name
Author-email: Kevin Denamganai <denamganai.kevin@gmail.com>
Project-URL: Homepage, https://github.com/Near32/wandb_tsbw
Keywords: tensorflow,tensorboard,pytorch,wandb,logging,machine learning
Classifier: Development Status :: 3 - Alpha
Classifier: Intended Audience :: Developers
Classifier: Intended Audience :: Science/Research
Classifier: License :: OSI Approved :: MIT License
Classifier: Programming Language :: Python :: 3
Classifier: Programming Language :: Python :: 3.6
Classifier: Programming Language :: Python :: 3.7
Classifier: Programming Language :: Python :: 3.8
Classifier: Programming Language :: Python :: 3.9
Classifier: Topic :: Scientific/Engineering :: Artificial Intelligence
Requires-Python: >=3.6
Requires-Dist: wandb>=0.12.0
Requires-Dist: numpy>=1.19.0
Dynamic: author
Dynamic: home-page
Dynamic: requires-python
